{"data":{"T1IM":{"Queue":{"QueueLength":0,"WaitDisplay":120},"Desk":{"ProcessTime":0,"QueueLength":0},"Error":{}},"T1DE_5a-9":{"Queue":{"QueueLength":108,"WaitDisplay":420},"Desk":{"ProcessTime":35},"Error":{}},"T1DE_5":{"Queue":{"QueueLength":2,"WaitDisplay":0},"Desk":{"ProcessTime":0},"Error":{}},"T1DE_1-4":{"Queue":{"QueueLength":31,"WaitDisplay":60},"Desk":{"ProcessTime":46},"Error":{}},"T1VI":{"Queue":{"QueueLength":0,"WaitDisplay":60},"Desk":{"ProcessTime":0},"Error":{}},"T1BD":{"Queue":{"QueueLength":0,"WaitDisplay":60},"Desk":{"ProcessTime":0},"Error":{}},"T1EM":{"Queue":{"QueueLength":12,"WaitDisplay":120},"Desk":{"ProcessTime":135},"Error":{}},"T1DS_Right":{"Queue":{"QueueLength":11,"WaitDisplay":300,"recommendation":{"bucket":"7","reference":"Lane 10+11","data":{"QueueId":"1021","QueueLength":"9","WaitB":"295","WaitF":"264","WaitDisplay":240,"Throughput":"74","ForwExits":"233186"},"code":"10+11"}},"Desk":{},"Error":{}},"T1IS":{"Queue":{"QueueLength":60,"WaitDisplay":600,"recommendation":{"data":{"WaitDisplay":999999}}},"Desk":{},"Error":{}},"T1DS_Left":{"Queue":{"QueueLength":35,"WaitDisplay":300,"recommendation":{"bucket":"1","reference":"Lane 1","data":{"QueueId":"1012","QueueLength":"6","WaitB":"392","WaitF":"98","WaitDisplay":120,"Throughput":"260","ForwExits":"73356"},"code":"1"}},"Desk":{"QueueLength":27,"ProcessTime":33},"Error":{}},"T1CI_01-33":{"6E":{"drilldown":[{"key":"Counter 13","QueueLength":"84","WaitDisplay":"240","ProcessTime":"56"},{"key":"Counter 14","QueueLength":"84","WaitDisplay":"240","ProcessTime":"0"},{"key":"Counter 15","QueueLength":"84","WaitDisplay":"240","ProcessTime":"0"},{"key":"Counter 16","QueueLength":"84","WaitDisplay":"240","ProcessTime":"0"},{"key":"Counter 17","QueueLength":"84","WaitDisplay":"240","ProcessTime":"0"},{"key":"Counter 18","QueueLength":"84","WaitDisplay":"240","ProcessTime":"0"},{"key":"Counter 19","QueueLength":"84","WaitDisplay":"240","ProcessTime":"59"},{"key":"Counter 20","QueueLength":"84","WaitDisplay":"240","ProcessTime":"53"},{"key":"Counter 21","QueueLength":"84","WaitDisplay":"240","ProcessTime":"0"},{"key":"Counter 22","QueueLength":"84","WaitDisplay":"240","ProcessTime":"52"},{"key":"Counter 23","QueueLength":"84","WaitDisplay":"240","ProcessTime":"0"},{"key":"Counter 24","QueueLength":"84","WaitDisplay":"240","ProcessTime":"37"},{"key":"Counter 25","QueueLength":"84","WaitDisplay":"240","ProcessTime":"45"},{"key":"Counter 26","QueueLength":"84","WaitDisplay":"240","ProcessTime":"0"},{"key":"Counter 27","QueueLength":"84","WaitDisplay":"240","ProcessTime":"0"},{"key":"Counter 28","QueueLength":"84","WaitDisplay":"240","ProcessTime":"94"},{"key":"Counter 29","QueueLength":"84","WaitDisplay":"240","ProcessTime":"82"},{"key":"Counter 30","QueueLength":"84","WaitDisplay":"240","ProcessTime":"61"},{"key":"Counter 31","QueueLength":"84","WaitDisplay":"240","ProcessTime":"68"},{"key":"Counter 32","QueueLength":"84","WaitDisplay":"240","ProcessTime":"92"},{"key":"Counter 33","QueueLength":"84","WaitDisplay":"240","ProcessTime":"121"}],"QueueLength":84,"WaitDisplay":240,"ProcessTime":121},"SG":{"drilldown":[{"key":"Counter 01","QueueLength":"4","WaitDisplay":"120","ProcessTime":"0"},{"key":"Counter 02","QueueLength":"4","WaitDisplay":"120","ProcessTime":"0"},{"key":"Counter 03","QueueLength":"4","WaitDisplay":"120","ProcessTime":"106"}],"QueueLength":4,"WaitDisplay":120,"ProcessTime":106}},"T1CI_34-86":{"EK":{"drilldown":[{"key":"Counter 80","QueueLength":"34","WaitDisplay":"480","ProcessTime":"0"},{"key":"Counter 81","QueueLength":"34","WaitDisplay":"480","ProcessTime":"52"},{"key":"Counter 82","QueueLength":"34","WaitDisplay":"480","ProcessTime":"0"},{"key":"Counter 83","QueueLength":"34","WaitDisplay":"480","ProcessTime":"0"},{"key":"Counter 84","QueueLength":"34","WaitDisplay":"480","ProcessTime":"122"},{"key":"Counter 85","QueueLength":"34","WaitDisplay":"480","ProcessTime":"47"},{"key":"Counter 86","QueueLength":"34","WaitDisplay":"480","ProcessTime":"61"}],"QueueLength":34,"WaitDisplay":480,"ProcessTime":122},"G8":{"drilldown":[{"key":"Counter 51","QueueLength":"4","WaitDisplay":"60","ProcessTime":"0"},{"key":"Counter 52","QueueLength":"4","WaitDisplay":"60","ProcessTime":"59"},{"key":"Counter 53","QueueLength":"4","WaitDisplay":"60","ProcessTime":"47"},{"key":"Counter 54","QueueLength":"4","WaitDisplay":"60","ProcessTime":"24"},{"key":"Counter 55","QueueLength":"4","WaitDisplay":"60","ProcessTime":"0"},{"key":"Counter 56","QueueLength":"4","WaitDisplay":"60","ProcessTime":"0"}],"QueueLength":4,"WaitDisplay":60,"ProcessTime":59},"UK":{"drilldown":[{"key":"Counter 45","QueueLength":"9","WaitDisplay":"120","ProcessTime":"159"},{"key":"Counter 46","QueueLength":"9","WaitDisplay":"120","ProcessTime":"31"},{"key":"Counter 47","QueueLength":"9","WaitDisplay":"120","ProcessTime":"63"},{"key":"Counter 48","QueueLength":"9","WaitDisplay":"120","ProcessTime":"0"},{"key":"Counter 49","QueueLength":"9","WaitDisplay":"120","ProcessTime":"0"},{"key":"Counter 50","QueueLength":"9","WaitDisplay":"120","ProcessTime":"0"}],"QueueLength":9,"WaitDisplay":120,"ProcessTime":159},"WY":{"drilldown":[{"key":"Counter 71","QueueLength":"0","WaitDisplay":"0","ProcessTime":"58"},{"key":"Counter 73","QueueLength":"0","WaitDisplay":"0","ProcessTime":"0"},{"key":"Counter 74","QueueLength":"0","WaitDisplay":"0","ProcessTime":"0"},{"key":"Counter 75","QueueLength":"0","WaitDisplay":"0","ProcessTime":"0"}],"QueueLength":0,"WaitDisplay":0,"ProcessTime":58},"QP":{"drilldown":[{"key":"Counter 63","QueueLength":"20","WaitDisplay":"180","ProcessTime":"44"},{"key":"Counter 64","QueueLength":"20","WaitDisplay":"180","ProcessTime":"0"},{"key":"Counter 65","QueueLength":"20","WaitDisplay":"180","ProcessTime":"25"},{"key":"Counter 66","QueueLength":"20","WaitDisplay":"180","ProcessTime":"43"},{"key":"Counter 67","QueueLength":"20","WaitDisplay":"180","ProcessTime":"0"},{"key":"Counter 68","QueueLength":"20","WaitDisplay":"180","ProcessTime":"33"},{"key":"Counter 69","QueueLength":"20","WaitDisplay":"180","ProcessTime":"99"},{"key":"Counter 70","QueueLength":"20","WaitDisplay":"180","ProcessTime":"74"}],"QueueLength":20,"WaitDisplay":180,"ProcessTime":99},"SV":{"drilldown":[{"key":"Counter 37","QueueLength":"0","WaitDisplay":"0","ProcessTime":"176"},{"key":"Counter 38","QueueLength":"0","WaitDisplay":"0","ProcessTime":"0"},{"key":"Counter 39","QueueLength":"0","WaitDisplay":"0","ProcessTime":"0"},{"key":"Counter 40","QueueLength":"0","WaitDisplay":"0","ProcessTime":"0"},{"key":"Counter 41","QueueLength":"0","WaitDisplay":"0","ProcessTime":"0"},{"key":"Counter 42","QueueLength":"0","WaitDisplay":"0","ProcessTime":"0"},{"key":"Counter 43","QueueLength":"0","WaitDisplay":"0","ProcessTime":"36"}],"QueueLength":0,"WaitDisplay":0,"ProcessTime":176}}},"metadata":{"units":{"QueueLength":"#","WaitDisplay":"seconds","ProcessTime":"seconds"}},"status":200,"type":"success","message":"Data Fetched Successfully"}