{"data":{"T1IM":{"Queue":{"QueueLength":0,"WaitDisplay":120},"Desk":{"ProcessTime":12,"QueueLength":0},"Error":{}},"T1DE_5a-9":{"Queue":{"QueueLength":50,"WaitDisplay":240},"Desk":{"ProcessTime":33},"Error":{}},"T1DE_5":{"Queue":{"QueueLength":1,"WaitDisplay":0},"Desk":{"ProcessTime":0},"Error":{}},"T1DE_1-4":{"Queue":{"QueueLength":49,"WaitDisplay":120},"Desk":{"ProcessTime":54},"Error":{}},"T1VI":{"Queue":{"QueueLength":1,"WaitDisplay":60},"Desk":{"ProcessTime":0},"Error":{}},"T1BD":{"Queue":{"QueueLength":0,"WaitDisplay":60},"Desk":{"ProcessTime":0},"Error":{}},"T1EM":{"Queue":{"QueueLength":0,"WaitDisplay":0},"Desk":{"ProcessTime":72},"Error":{}},"T1DS_Right":{"Queue":{"QueueLength":11,"WaitDisplay":360,"recommendation":{"bucket":"7","reference":"Lane 10+11","data":{"QueueId":"1022","QueueLength":"11","WaitB":"109","WaitF":"351","WaitDisplay":360,"Throughput":"24","ForwExits":"363072"},"code":"10+11"}},"Desk":{},"Error":{}},"T1IS":{"Queue":{"QueueLength":34,"WaitDisplay":540,"recommendation":{"data":{"WaitDisplay":999999}}},"Desk":{},"Error":{}},"T1DS_Left":{"Queue":{"QueueLength":24,"WaitDisplay":420,"recommendation":{"bucket":"1","reference":"Lane 1","data":{"QueueId":"1012","QueueLength":"3","WaitB":"137","WaitF":"67","WaitDisplay":60,"Throughput":"173","ForwExits":"62798"},"code":"1"}},"Desk":{"QueueLength":14,"ProcessTime":25},"Error":{}},"T1CI_34-86":{"EK":{"drilldown":[{"key":"Counter 79","QueueLength":"27","WaitDisplay":"300","ProcessTime":"0"},{"key":"Counter 80","QueueLength":"27","WaitDisplay":"300","ProcessTime":"0"},{"key":"Counter 81","QueueLength":"27","WaitDisplay":"300","ProcessTime":"0"},{"key":"Counter 82","QueueLength":"27","WaitDisplay":"300","ProcessTime":"0"},{"key":"Counter 83","QueueLength":"27","WaitDisplay":"300","ProcessTime":"0"},{"key":"Counter 84","QueueLength":"27","WaitDisplay":"300","ProcessTime":"175"},{"key":"Counter 85","QueueLength":"27","WaitDisplay":"300","ProcessTime":"0"},{"key":"Counter 86","QueueLength":"27","WaitDisplay":"300","ProcessTime":"49"}],"QueueLength":27,"WaitDisplay":300,"ProcessTime":175},"G8":{"drilldown":[{"key":"Counter 52","QueueLength":"6","WaitDisplay":"120","ProcessTime":"0"},{"key":"Counter 53","QueueLength":"6","WaitDisplay":"120","ProcessTime":"0"},{"key":"Counter 54","QueueLength":"6","WaitDisplay":"120","ProcessTime":"0"},{"key":"Counter 55","QueueLength":"6","WaitDisplay":"120","ProcessTime":"57"},{"key":"Counter 56","QueueLength":"6","WaitDisplay":"120","ProcessTime":"53"},{"key":"Counter 57","QueueLength":"6","WaitDisplay":"120","ProcessTime":"0"}],"QueueLength":6,"WaitDisplay":120,"ProcessTime":57},"WY":{"drilldown":[{"key":"Counter 71","QueueLength":"19","WaitDisplay":"360","ProcessTime":"0"},{"key":"Counter 72","QueueLength":"19","WaitDisplay":"360","ProcessTime":"0"},{"key":"Counter 73","QueueLength":"19","WaitDisplay":"360","ProcessTime":"35"},{"key":"Counter 74","QueueLength":"19","WaitDisplay":"360","ProcessTime":"0"},{"key":"Counter 75","QueueLength":"19","WaitDisplay":"360","ProcessTime":"0"}],"QueueLength":19,"WaitDisplay":360,"ProcessTime":35},"QP":{"drilldown":[{"key":"Counter 63","QueueLength":"20","WaitDisplay":"180","ProcessTime":"0"},{"key":"Counter 64","QueueLength":"20","WaitDisplay":"180","ProcessTime":"79"},{"key":"Counter 65","QueueLength":"20","WaitDisplay":"180","ProcessTime":"0"},{"key":"Counter 66","QueueLength":"20","WaitDisplay":"180","ProcessTime":"0"},{"key":"Counter 67","QueueLength":"20","WaitDisplay":"180","ProcessTime":"0"},{"key":"Counter 68","QueueLength":"20","WaitDisplay":"180","ProcessTime":"0"},{"key":"Counter 69","QueueLength":"20","WaitDisplay":"180","ProcessTime":"0"},{"key":"Counter 70","QueueLength":"20","WaitDisplay":"180","ProcessTime":"0"}],"QueueLength":20,"WaitDisplay":180,"ProcessTime":79}},"T1CI_01-33":{"6E":{"drilldown":[{"key":"Counter 13","QueueLength":"63","WaitDisplay":"240","ProcessTime":"0"},{"key":"Counter 14","QueueLength":"63","WaitDisplay":"240","ProcessTime":"0"},{"key":"Counter 15","QueueLength":"63","WaitDisplay":"240","ProcessTime":"41"},{"key":"Counter 16","QueueLength":"63","WaitDisplay":"240","ProcessTime":"60"},{"key":"Counter 17","QueueLength":"63","WaitDisplay":"240","ProcessTime":"0"},{"key":"Counter 18","QueueLength":"63","WaitDisplay":"240","ProcessTime":"0"},{"key":"Counter 19","QueueLength":"63","WaitDisplay":"240","ProcessTime":"0"},{"key":"Counter 20","QueueLength":"63","WaitDisplay":"240","ProcessTime":"0"},{"key":"Counter 21","QueueLength":"63","WaitDisplay":"240","ProcessTime":"0"},{"key":"Counter 22","QueueLength":"63","WaitDisplay":"240","ProcessTime":"0"},{"key":"Counter 23","QueueLength":"63","WaitDisplay":"240","ProcessTime":"48"},{"key":"Counter 24","QueueLength":"63","WaitDisplay":"240","ProcessTime":"0"},{"key":"Counter 25","QueueLength":"63","WaitDisplay":"240","ProcessTime":"62"},{"key":"Counter 26","QueueLength":"63","WaitDisplay":"240","ProcessTime":"0"},{"key":"Counter 27","QueueLength":"63","WaitDisplay":"240","ProcessTime":"71"},{"key":"Counter 28","QueueLength":"63","WaitDisplay":"240","ProcessTime":"0"},{"key":"Counter 29","QueueLength":"63","WaitDisplay":"240","ProcessTime":"105"},{"key":"Counter 30","QueueLength":"63","WaitDisplay":"240","ProcessTime":"47"},{"key":"Counter 31","QueueLength":"63","WaitDisplay":"240","ProcessTime":"41"},{"key":"Counter 32","QueueLength":"63","WaitDisplay":"240","ProcessTime":"122"},{"key":"Counter 33","QueueLength":"63","WaitDisplay":"240","ProcessTime":"0"}],"QueueLength":63,"WaitDisplay":240,"ProcessTime":122},"AI":{"drilldown":[{"key":"Counter 06","QueueLength":"3","WaitDisplay":"60","ProcessTime":"0"},{"key":"Counter 07","QueueLength":"3","WaitDisplay":"60","ProcessTime":"0"},{"key":"Counter 08","QueueLength":"3","WaitDisplay":"60","ProcessTime":"94"},{"key":"Counter 09","QueueLength":"3","WaitDisplay":"60","ProcessTime":"89"},{"key":"Counter 10","QueueLength":"3","WaitDisplay":"60","ProcessTime":"61"}],"QueueLength":3,"WaitDisplay":60,"ProcessTime":94},"SG":{"drilldown":[{"key":"Counter 01","QueueLength":"1","WaitDisplay":"60","ProcessTime":"97"},{"key":"Counter 02","QueueLength":"1","WaitDisplay":"60","ProcessTime":"0"},{"key":"Counter 03","QueueLength":"1","WaitDisplay":"60","ProcessTime":"151"}],"QueueLength":1,"WaitDisplay":60,"ProcessTime":151},"9I":{"drilldown":[{"key":"Counter 11","QueueLength":"0","WaitDisplay":"0","ProcessTime":"0"},{"key":"Counter 12","QueueLength":"0","WaitDisplay":"0","ProcessTime":"0"}],"QueueLength":0,"WaitDisplay":0,"ProcessTime":0}}},"metadata":{"units":{"QueueLength":"#","WaitDisplay":"seconds","ProcessTime":"seconds"}},"status":200,"type":"success","message":"Data Fetched Successfully"}