{"data":{"T1IM":{"Queue":{"QueueLength":0,"WaitDisplay":120},"Desk":{"ProcessTime":141,"QueueLength":0},"Error":{}},"T1VI":{"Queue":{"QueueLength":7,"WaitDisplay":180},"Desk":{"ProcessTime":248},"Error":{}},"T1DE_1-4":{"Queue":{"QueueLength":25,"WaitDisplay":120},"Desk":{"ProcessTime":46},"Error":{}},"T1DE_5":{"Queue":{"QueueLength":1,"WaitDisplay":60},"Desk":{"ProcessTime":0},"Error":{}},"T1DE_5a-9":{"Queue":{"QueueLength":27,"WaitDisplay":60},"Desk":{"ProcessTime":66},"Error":{}},"T1EM":{"Queue":{"QueueLength":91,"WaitDisplay":540},"Desk":{"ProcessTime":153},"Error":{}},"T1BD":{"Queue":{"QueueLength":1,"WaitDisplay":120},"Desk":{"ProcessTime":0},"Error":{}},"T1DS_Right":{"Queue":{"QueueLength":0,"WaitDisplay":120,"recommendation":{"data":{"WaitDisplay":999999}}},"Desk":{},"Error":{}},"T1IS":{"Queue":{"QueueLength":19,"WaitDisplay":360,"recommendation":{"data":{"WaitDisplay":999999}}},"Desk":{},"Error":{}},"T1DS_Left":{"Queue":{"QueueLength":9,"WaitDisplay":120,"recommendation":{"bucket":"3","reference":"Lane 4+5","data":{"QueueId":"1016","QueueLength":"2","WaitB":"13","WaitF":"42","WaitDisplay":120,"Throughput":"49","ForwExits":"77521"},"code":"4+5"}},"Desk":{"QueueLength":8,"ProcessTime":17},"Error":{}},"T1CI_34-86":{"EK":{"drilldown":[{"key":"Counter 79","QueueLength":"42","WaitDisplay":"480","ProcessTime":"138"},{"key":"Counter 80","QueueLength":"42","WaitDisplay":"480","ProcessTime":"0"},{"key":"Counter 81","QueueLength":"42","WaitDisplay":"480","ProcessTime":"208"},{"key":"Counter 82","QueueLength":"42","WaitDisplay":"480","ProcessTime":"0"},{"key":"Counter 83","QueueLength":"42","WaitDisplay":"480","ProcessTime":"0"},{"key":"Counter 84","QueueLength":"42","WaitDisplay":"480","ProcessTime":"0"},{"key":"Counter 85","QueueLength":"42","WaitDisplay":"480","ProcessTime":"0"},{"key":"Counter 86","QueueLength":"42","WaitDisplay":"480","ProcessTime":"0"}],"QueueLength":42,"WaitDisplay":480,"ProcessTime":208},"LH":{"drilldown":[{"key":"Counter 43","QueueLength":"53","WaitDisplay":"540","ProcessTime":"0"},{"key":"Counter 44","QueueLength":"53","WaitDisplay":"540","ProcessTime":"0"},{"key":"Counter 45","QueueLength":"53","WaitDisplay":"540","ProcessTime":"0"},{"key":"Counter 46","QueueLength":"53","WaitDisplay":"540","ProcessTime":"114"},{"key":"Counter 47","QueueLength":"53","WaitDisplay":"540","ProcessTime":"0"},{"key":"Counter 48","QueueLength":"53","WaitDisplay":"540","ProcessTime":"0"},{"key":"Counter 49","QueueLength":"53","WaitDisplay":"540","ProcessTime":"74"},{"key":"Counter 50","QueueLength":"53","WaitDisplay":"540","ProcessTime":"0"}],"QueueLength":53,"WaitDisplay":540,"ProcessTime":114},"QR":{"drilldown":[{"key":"Counter 64","QueueLength":"13","WaitDisplay":"180","ProcessTime":"58"},{"key":"Counter 65","QueueLength":"13","WaitDisplay":"180","ProcessTime":"0"},{"key":"Counter 66","QueueLength":"13","WaitDisplay":"180","ProcessTime":"0"},{"key":"Counter 68","QueueLength":"13","WaitDisplay":"180","ProcessTime":"98"},{"key":"Counter 69","QueueLength":"13","WaitDisplay":"180","ProcessTime":"0"}],"QueueLength":13,"WaitDisplay":180,"ProcessTime":98},"SQ":{"drilldown":[{"key":"Counter 71","QueueLength":"24","WaitDisplay":"240","ProcessTime":"0"},{"key":"Counter 72","QueueLength":"24","WaitDisplay":"240","ProcessTime":"0"},{"key":"Counter 73","QueueLength":"24","WaitDisplay":"240","ProcessTime":"0"},{"key":"Counter 74","QueueLength":"24","WaitDisplay":"240","ProcessTime":"34"},{"key":"Counter 75","QueueLength":"24","WaitDisplay":"240","ProcessTime":"0"},{"key":"Counter 76","QueueLength":"24","WaitDisplay":"240","ProcessTime":"0"},{"key":"Counter 77","QueueLength":"24","WaitDisplay":"240","ProcessTime":"0"},{"key":"Counter 78","QueueLength":"24","WaitDisplay":"240","ProcessTime":"0"}],"QueueLength":24,"WaitDisplay":240,"ProcessTime":34},"GF":{"drilldown":[{"key":"Counter 40","QueueLength":"1","WaitDisplay":"60","ProcessTime":"0"},{"key":"Counter 41","QueueLength":"1","WaitDisplay":"60","ProcessTime":"0"},{"key":"Counter 42","QueueLength":"1","WaitDisplay":"60","ProcessTime":"0"}],"QueueLength":1,"WaitDisplay":60,"ProcessTime":0}},"T1CI_01-33":{"6E":{"drilldown":[{"key":"Counter 21","QueueLength":"8","WaitDisplay":"60","ProcessTime":"0"},{"key":"Counter 22","QueueLength":"8","WaitDisplay":"60","ProcessTime":"0"},{"key":"Counter 23","QueueLength":"8","WaitDisplay":"60","ProcessTime":"0"},{"key":"Counter 24","QueueLength":"8","WaitDisplay":"60","ProcessTime":"0"},{"key":"Counter 25","QueueLength":"8","WaitDisplay":"60","ProcessTime":"34"},{"key":"Counter 26","QueueLength":"8","WaitDisplay":"60","ProcessTime":"81"},{"key":"Counter 27","QueueLength":"8","WaitDisplay":"60","ProcessTime":"0"},{"key":"Counter 28","QueueLength":"8","WaitDisplay":"60","ProcessTime":"63"},{"key":"Counter 29","QueueLength":"8","WaitDisplay":"60","ProcessTime":"33"},{"key":"Counter 30","QueueLength":"8","WaitDisplay":"60","ProcessTime":"0"},{"key":"Counter 31","QueueLength":"8","WaitDisplay":"60","ProcessTime":"0"},{"key":"Counter 32","QueueLength":"8","WaitDisplay":"60","ProcessTime":"0"},{"key":"Counter 33","QueueLength":"8","WaitDisplay":"60","ProcessTime":"0"}],"QueueLength":8,"WaitDisplay":60,"ProcessTime":81},"AF":{"drilldown":[{"key":"Counter 01","QueueLength":"4","WaitDisplay":"60","ProcessTime":"75"},{"key":"Counter 02","QueueLength":"4","WaitDisplay":"60","ProcessTime":"0"},{"key":"Counter 03","QueueLength":"4","WaitDisplay":"60","ProcessTime":"0"},{"key":"Counter 04","QueueLength":"4","WaitDisplay":"60","ProcessTime":"0"},{"key":"Counter 05","QueueLength":"4","WaitDisplay":"60","ProcessTime":"23"},{"key":"Counter 06","QueueLength":"4","WaitDisplay":"60","ProcessTime":"0"}],"QueueLength":4,"WaitDisplay":60,"ProcessTime":75},"EY":{"drilldown":[{"key":"Counter 13","QueueLength":"0","WaitDisplay":"0","ProcessTime":"0"},{"key":"Counter 14","QueueLength":"0","WaitDisplay":"0","ProcessTime":"0"},{"key":"Counter 15","QueueLength":"0","WaitDisplay":"0","ProcessTime":"0"},{"key":"Counter 16","QueueLength":"0","WaitDisplay":"0","ProcessTime":"0"},{"key":"Counter 17","QueueLength":"0","WaitDisplay":"0","ProcessTime":"0"},{"key":"Counter 18","QueueLength":"0","WaitDisplay":"0","ProcessTime":"0"},{"key":"Counter 19","QueueLength":"0","WaitDisplay":"0","ProcessTime":"29"},{"key":"Counter 20","QueueLength":"0","WaitDisplay":"0","ProcessTime":"0"}],"QueueLength":0,"WaitDisplay":0,"ProcessTime":29},"KL":{"drilldown":[{"key":"Counter 07","QueueLength":"10","WaitDisplay":"180","ProcessTime":"0"},{"key":"Counter 08","QueueLength":"10","WaitDisplay":"180","ProcessTime":"0"},{"key":"Counter 09","QueueLength":"10","WaitDisplay":"180","ProcessTime":"0"},{"key":"Counter 10","QueueLength":"10","WaitDisplay":"180","ProcessTime":"0"},{"key":"Counter 11","QueueLength":"10","WaitDisplay":"180","ProcessTime":"0"},{"key":"Counter 12","QueueLength":"10","WaitDisplay":"180","ProcessTime":"37"}],"QueueLength":10,"WaitDisplay":180,"ProcessTime":37}}},"metadata":{"units":{"QueueLength":"#","WaitDisplay":"seconds","ProcessTime":"seconds"}},"status":200,"type":"success","message":"Data Fetched Successfully"}