{"data":{"T1IM":{"Queue":{"QueueLength":0,"WaitDisplay":120},"Desk":{"ProcessTime":0,"QueueLength":0},"Error":{}},"T1DE_5":{"Queue":{"QueueLength":1,"WaitDisplay":0},"Desk":{"ProcessTime":0},"Error":{}},"T1VI":{"Queue":{"QueueLength":0,"WaitDisplay":0},"Desk":{"ProcessTime":0},"Error":{}},"T1DE_1-4":{"Queue":{"QueueLength":30,"WaitDisplay":60},"Desk":{"ProcessTime":18},"Error":{}},"T1DE_5a-9":{"Queue":{"QueueLength":56,"WaitDisplay":120},"Desk":{"ProcessTime":30},"Error":{}},"T1EM":{"Queue":{"QueueLength":3,"WaitDisplay":0},"Desk":{"ProcessTime":199},"Error":{}},"T1BD":{"Queue":{"QueueLength":5,"WaitDisplay":180},"Desk":{"ProcessTime":0},"Error":{}},"T1DS_Right":{"Queue":{"QueueLength":100,"WaitDisplay":4200,"recommendation":{"bucket":"8","reference":"Lane 12+13","data":{"QueueId":"1024","QueueLength":"37","WaitB":"574","WaitF":"936","WaitDisplay":900,"Throughput":"111","ForwExits":"223645"},"code":"12+13"}},"Desk":{},"Error":{}},"T1IS":{"Queue":{"QueueLength":11,"WaitDisplay":180,"recommendation":{"data":{"WaitDisplay":999999}}},"Desk":{},"Error":{}},"T1DS_Left":{"Queue":{"QueueLength":97,"WaitDisplay":900,"recommendation":{"bucket":"2","reference":"Lane 2+3","data":{"QueueId":"1014","QueueLength":"42","WaitB":"372","WaitF":"254","WaitDisplay":240,"Throughput":"359","ForwExits":"37538"},"code":"2+3"}},"Desk":{"QueueLength":74,"ProcessTime":25},"Error":{}},"T1CI_01-33":{"6E":{"drilldown":[{"key":"Counter 13","QueueLength":"74","WaitDisplay":"240","ProcessTime":"61"},{"key":"Counter 14","QueueLength":"74","WaitDisplay":"240","ProcessTime":"0"},{"key":"Counter 15","QueueLength":"74","WaitDisplay":"240","ProcessTime":"22"},{"key":"Counter 16","QueueLength":"74","WaitDisplay":"240","ProcessTime":"56"},{"key":"Counter 17","QueueLength":"74","WaitDisplay":"240","ProcessTime":"0"},{"key":"Counter 18","QueueLength":"74","WaitDisplay":"240","ProcessTime":"0"},{"key":"Counter 19","QueueLength":"74","WaitDisplay":"240","ProcessTime":"121"},{"key":"Counter 20","QueueLength":"74","WaitDisplay":"240","ProcessTime":"0"},{"key":"Counter 21","QueueLength":"74","WaitDisplay":"240","ProcessTime":"0"},{"key":"Counter 22","QueueLength":"74","WaitDisplay":"240","ProcessTime":"0"},{"key":"Counter 23","QueueLength":"74","WaitDisplay":"240","ProcessTime":"51"},{"key":"Counter 24","QueueLength":"74","WaitDisplay":"240","ProcessTime":"0"},{"key":"Counter 25","QueueLength":"74","WaitDisplay":"240","ProcessTime":"52"},{"key":"Counter 26","QueueLength":"74","WaitDisplay":"240","ProcessTime":"46"},{"key":"Counter 27","QueueLength":"74","WaitDisplay":"240","ProcessTime":"55"},{"key":"Counter 28","QueueLength":"74","WaitDisplay":"240","ProcessTime":"58"},{"key":"Counter 29","QueueLength":"74","WaitDisplay":"240","ProcessTime":"77"},{"key":"Counter 30","QueueLength":"74","WaitDisplay":"240","ProcessTime":"95"},{"key":"Counter 31","QueueLength":"74","WaitDisplay":"240","ProcessTime":"0"},{"key":"Counter 32","QueueLength":"74","WaitDisplay":"240","ProcessTime":"0"},{"key":"Counter 33","QueueLength":"74","WaitDisplay":"240","ProcessTime":"0"}],"QueueLength":74,"WaitDisplay":240,"ProcessTime":121},"AI":{"drilldown":[{"key":"Counter 06","QueueLength":"5","WaitDisplay":"60","ProcessTime":"0"},{"key":"Counter 07","QueueLength":"5","WaitDisplay":"60","ProcessTime":"0"},{"key":"Counter 08","QueueLength":"5","WaitDisplay":"60","ProcessTime":"0"},{"key":"Counter 09","QueueLength":"5","WaitDisplay":"60","ProcessTime":"0"},{"key":"Counter 10","QueueLength":"5","WaitDisplay":"60","ProcessTime":"0"}],"QueueLength":5,"WaitDisplay":60,"ProcessTime":0}},"T1CI_34-86":{"6E":{"drilldown":[{"key":"Counter 59","QueueLength":"1","WaitDisplay":"60","ProcessTime":"63"},{"key":"Counter 60","QueueLength":"1","WaitDisplay":"60","ProcessTime":"0"},{"key":"Counter 61","QueueLength":"1","WaitDisplay":"60","ProcessTime":"0"}],"QueueLength":1,"WaitDisplay":60,"ProcessTime":63},"G8":{"drilldown":[{"key":"Counter 51","QueueLength":"0","WaitDisplay":"0","ProcessTime":"0"},{"key":"Counter 52","QueueLength":"0","WaitDisplay":"0","ProcessTime":"0"},{"key":"Counter 53","QueueLength":"0","WaitDisplay":"0","ProcessTime":"0"},{"key":"Counter 54","QueueLength":"0","WaitDisplay":"0","ProcessTime":"0"},{"key":"Counter 55","QueueLength":"0","WaitDisplay":"0","ProcessTime":"0"},{"key":"Counter 56","QueueLength":"0","WaitDisplay":"0","ProcessTime":"45"},{"key":"Counter 57","QueueLength":"0","WaitDisplay":"0","ProcessTime":"128"},{"key":"Counter 58","QueueLength":"0","WaitDisplay":"0","ProcessTime":"0"}],"QueueLength":0,"WaitDisplay":0,"ProcessTime":128},"I5":{"drilldown":[{"key":"Counter 34","QueueLength":"77","WaitDisplay":"540","ProcessTime":"0"},{"key":"Counter 35","QueueLength":"77","WaitDisplay":"540","ProcessTime":"76"},{"key":"Counter 36","QueueLength":"77","WaitDisplay":"540","ProcessTime":"53"},{"key":"Counter 37","QueueLength":"77","WaitDisplay":"540","ProcessTime":"27"},{"key":"Counter 38","QueueLength":"77","WaitDisplay":"540","ProcessTime":"0"},{"key":"Counter 39","QueueLength":"77","WaitDisplay":"540","ProcessTime":"0"},{"key":"Counter 40","QueueLength":"77","WaitDisplay":"540","ProcessTime":"106"}],"QueueLength":77,"WaitDisplay":540,"ProcessTime":106},"QF":{"drilldown":[{"key":"Counter 75","QueueLength":"1","WaitDisplay":"0","ProcessTime":"0"},{"key":"Counter 76","QueueLength":"1","WaitDisplay":"0","ProcessTime":"0"},{"key":"Counter 77","QueueLength":"1","WaitDisplay":"0","ProcessTime":"0"},{"key":"Counter 78","QueueLength":"1","WaitDisplay":"0","ProcessTime":"0"},{"key":"Counter 79","QueueLength":"1","WaitDisplay":"0","ProcessTime":"0"},{"key":"Counter 80","QueueLength":"1","WaitDisplay":"0","ProcessTime":"0"},{"key":"Counter 81","QueueLength":"1","WaitDisplay":"0","ProcessTime":"0"},{"key":"Counter 82","QueueLength":"1","WaitDisplay":"0","ProcessTime":"0"},{"key":"Counter 83","QueueLength":"1","WaitDisplay":"0","ProcessTime":"0"}],"QueueLength":1,"WaitDisplay":0,"ProcessTime":0},"QP":{"drilldown":[{"key":"Counter 63","QueueLength":"24","WaitDisplay":"240","ProcessTime":"0"},{"key":"Counter 64","QueueLength":"24","WaitDisplay":"240","ProcessTime":"0"},{"key":"Counter 65","QueueLength":"24","WaitDisplay":"240","ProcessTime":"0"},{"key":"Counter 66","QueueLength":"24","WaitDisplay":"240","ProcessTime":"0"},{"key":"Counter 67","QueueLength":"24","WaitDisplay":"240","ProcessTime":"0"},{"key":"Counter 68","QueueLength":"24","WaitDisplay":"240","ProcessTime":"0"},{"key":"Counter 69","QueueLength":"24","WaitDisplay":"240","ProcessTime":"0"},{"key":"Counter 70","QueueLength":"24","WaitDisplay":"240","ProcessTime":"0"}],"QueueLength":24,"WaitDisplay":240,"ProcessTime":0}}},"metadata":{"units":{"QueueLength":"#","WaitDisplay":"seconds","ProcessTime":"seconds"}},"status":200,"type":"success","message":"Data Fetched Successfully"}