{"data":{"T1IM":{"Queue":{"QueueLength":148,"WaitDisplay":1020},"Desk":{"ProcessTime":184,"QueueLength":55},"Error":{}},"T1DE_5a-9":{"Queue":{"QueueLength":58,"WaitDisplay":240},"Desk":{"ProcessTime":163},"Error":{}},"T1VI":{"Queue":{"QueueLength":23,"WaitDisplay":300},"Desk":{"ProcessTime":0},"Error":{}},"T1DE_1-4":{"Queue":{"QueueLength":51,"WaitDisplay":120},"Desk":{"ProcessTime":20},"Error":{}},"T1DE_5":{"Queue":{"QueueLength":0,"WaitDisplay":0},"Desk":{"ProcessTime":0},"Error":{}},"T1EM":{"Queue":{"QueueLength":169,"WaitDisplay":600},"Desk":{"ProcessTime":139},"Error":{}},"T1BD":{"Queue":{"QueueLength":1,"WaitDisplay":60},"Desk":{"ProcessTime":0},"Error":{}},"T1DS_Right":{"Queue":{"QueueLength":14,"WaitDisplay":540,"recommendation":{"bucket":"7","reference":"Lane 10+11","data":{"QueueId":"1022","QueueLength":"14","WaitB":"177","WaitF":"534","WaitDisplay":540,"Throughput":"123","ForwExits":"332727"},"code":"10+11"}},"Desk":{},"Error":{}},"T1IS":{"Queue":{"QueueLength":108,"WaitDisplay":840,"recommendation":{"data":{"WaitDisplay":999999}}},"Desk":{},"Error":{}},"T1DS_Left":{"Queue":{"QueueLength":48,"WaitDisplay":600,"recommendation":{"bucket":"3","reference":"Lane 4+5","data":{"QueueId":"1015","QueueLength":"37","WaitB":"266","WaitF":"316","WaitDisplay":300,"Throughput":"260","ForwExits":"71125"},"code":"4+5"}},"Desk":{"QueueLength":44,"ProcessTime":15},"Error":{}},"T1CI_34-86":{"EK":{"drilldown":[{"key":"Counter 75","QueueLength":"0","WaitDisplay":"0","ProcessTime":"0"},{"key":"Counter 76","QueueLength":"0","WaitDisplay":"0","ProcessTime":"0"},{"key":"Counter 77","QueueLength":"0","WaitDisplay":"0","ProcessTime":"0"},{"key":"Counter 78","QueueLength":"0","WaitDisplay":"0","ProcessTime":"0"},{"key":"Counter 79","QueueLength":"0","WaitDisplay":"0","ProcessTime":"0"},{"key":"Counter 80","QueueLength":"0","WaitDisplay":"0","ProcessTime":"0"},{"key":"Counter 81","QueueLength":"0","WaitDisplay":"0","ProcessTime":"0"},{"key":"Counter 82","QueueLength":"0","WaitDisplay":"0","ProcessTime":"0"},{"key":"Counter 83","QueueLength":"0","WaitDisplay":"0","ProcessTime":"0"},{"key":"Counter 84","QueueLength":"0","WaitDisplay":"0","ProcessTime":"0"},{"key":"Counter 85","QueueLength":"0","WaitDisplay":"0","ProcessTime":"0"},{"key":"Counter 86","QueueLength":"0","WaitDisplay":"0","ProcessTime":"0"}],"QueueLength":0,"WaitDisplay":0,"ProcessTime":0},"I5":{"drilldown":[{"key":"Counter 34","QueueLength":"9","WaitDisplay":"120","ProcessTime":"0"},{"key":"Counter 35","QueueLength":"9","WaitDisplay":"120","ProcessTime":"50"},{"key":"Counter 36","QueueLength":"9","WaitDisplay":"120","ProcessTime":"67"},{"key":"Counter 37","QueueLength":"9","WaitDisplay":"120","ProcessTime":"42"}],"QueueLength":9,"WaitDisplay":120,"ProcessTime":67},"QP":{"QueueLength":-1,"WaitDisplay":-1,"ProcessTime":-1}},"T1CI_01-33":{"6E":{"drilldown":[{"key":"Counter 23","QueueLength":"88","WaitDisplay":"420","ProcessTime":"0"},{"key":"Counter 24","QueueLength":"88","WaitDisplay":"420","ProcessTime":"0"},{"key":"Counter 25","QueueLength":"88","WaitDisplay":"420","ProcessTime":"0"},{"key":"Counter 26","QueueLength":"88","WaitDisplay":"420","ProcessTime":"0"},{"key":"Counter 27","QueueLength":"88","WaitDisplay":"420","ProcessTime":"0"},{"key":"Counter 28","QueueLength":"88","WaitDisplay":"420","ProcessTime":"0"},{"key":"Counter 29","QueueLength":"88","WaitDisplay":"420","ProcessTime":"0"},{"key":"Counter 30","QueueLength":"88","WaitDisplay":"420","ProcessTime":"102"},{"key":"Counter 31","QueueLength":"88","WaitDisplay":"420","ProcessTime":"0"},{"key":"Counter 32","QueueLength":"88","WaitDisplay":"420","ProcessTime":"0"},{"key":"Counter 33","QueueLength":"88","WaitDisplay":"420","ProcessTime":"83"}],"QueueLength":88,"WaitDisplay":420,"ProcessTime":102},"EY":{"drilldown":[{"key":"Counter 13","QueueLength":"0","WaitDisplay":"0","ProcessTime":"0"},{"key":"Counter 14","QueueLength":"0","WaitDisplay":"0","ProcessTime":"0"},{"key":"Counter 15","QueueLength":"0","WaitDisplay":"0","ProcessTime":"0"},{"key":"Counter 16","QueueLength":"0","WaitDisplay":"0","ProcessTime":"48"},{"key":"Counter 17","QueueLength":"0","WaitDisplay":"0","ProcessTime":"25"},{"key":"Counter 18","QueueLength":"0","WaitDisplay":"0","ProcessTime":"0"}],"QueueLength":0,"WaitDisplay":0,"ProcessTime":48},"KU":{"drilldown":[{"key":"Counter 04","QueueLength":"16","WaitDisplay":"180","ProcessTime":"117"},{"key":"Counter 05","QueueLength":"16","WaitDisplay":"180","ProcessTime":"0"},{"key":"Counter 06","QueueLength":"16","WaitDisplay":"180","ProcessTime":"16"},{"key":"Counter 07","QueueLength":"16","WaitDisplay":"180","ProcessTime":"0"}],"QueueLength":16,"WaitDisplay":180,"ProcessTime":117}}},"metadata":{"units":{"QueueLength":"#","WaitDisplay":"seconds","ProcessTime":"seconds"}},"status":200,"type":"success","message":"Data Fetched Successfully"}