{"data":{"T1IM":{"Queue":{"QueueLength":0,"WaitDisplay":120},"Desk":{"ProcessTime":0,"QueueLength":0},"Error":{}},"T1DE_5":{"Queue":{"QueueLength":0,"WaitDisplay":0},"Desk":{"ProcessTime":68},"Error":{}},"T1DE_1-4":{"Queue":{"QueueLength":55,"WaitDisplay":120},"Desk":{"ProcessTime":117},"Error":{}},"T1DE_5a-9":{"Queue":{"QueueLength":19,"WaitDisplay":120},"Desk":{"ProcessTime":56},"Error":{}},"T1BD":{"Queue":{"QueueLength":0,"WaitDisplay":60},"Desk":{"ProcessTime":0},"Error":{}},"T1EM":{"Queue":{"QueueLength":14,"WaitDisplay":120},"Desk":{"ProcessTime":157},"Error":{}},"T1VI":{"Queue":{"QueueLength":0,"WaitDisplay":0},"Desk":{"ProcessTime":0},"Error":{}},"T1IS":{"Queue":{"QueueLength":12,"WaitDisplay":480,"recommendation":{"data":{"WaitDisplay":999999}}},"Desk":{},"Error":{}},"T1DS_Right":{"Queue":{"QueueLength":46,"WaitDisplay":1200,"recommendation":{"bucket":"7","reference":"Lane 10+11","data":{"QueueId":"1022","QueueLength":"46","WaitB":"100","WaitF":"1725","WaitDisplay":1200,"Throughput":"123","ForwExits":"344777"},"code":"10+11"}},"Desk":{},"Error":{}},"T1DS_Left":{"Queue":{"QueueLength":24,"WaitDisplay":540,"recommendation":{"bucket":"1","reference":"Lane 1","data":{"QueueId":"1012","QueueLength":"0","WaitB":"0","WaitF":"21","WaitDisplay":0,"Throughput":"0","ForwExits":"51249"},"code":"1"}},"Desk":{"QueueLength":16,"ProcessTime":24},"Error":{}},"T1CI_01-33":{"6E":{"drilldown":[{"key":"Counter 25","QueueLength":"44","WaitDisplay":"360","ProcessTime":"43"},{"key":"Counter 26","QueueLength":"44","WaitDisplay":"360","ProcessTime":"0"},{"key":"Counter 27","QueueLength":"44","WaitDisplay":"360","ProcessTime":"0"},{"key":"Counter 28","QueueLength":"44","WaitDisplay":"360","ProcessTime":"102"},{"key":"Counter 29","QueueLength":"44","WaitDisplay":"360","ProcessTime":"107"},{"key":"Counter 30","QueueLength":"44","WaitDisplay":"360","ProcessTime":"94"},{"key":"Counter 31","QueueLength":"44","WaitDisplay":"360","ProcessTime":"0"},{"key":"Counter 32","QueueLength":"44","WaitDisplay":"360","ProcessTime":"0"},{"key":"Counter 33","QueueLength":"44","WaitDisplay":"360","ProcessTime":"0"}],"QueueLength":44,"WaitDisplay":360,"ProcessTime":107},"AK":{"drilldown":[{"key":"Counter 03","QueueLength":"13","WaitDisplay":"180","ProcessTime":"0"},{"key":"Counter 04","QueueLength":"13","WaitDisplay":"180","ProcessTime":"0"},{"key":"Counter 05","QueueLength":"13","WaitDisplay":"180","ProcessTime":"0"},{"key":"Counter 06","QueueLength":"13","WaitDisplay":"180","ProcessTime":"0"}],"QueueLength":13,"WaitDisplay":180,"ProcessTime":0},"9I":{"drilldown":[{"key":"Counter 11","QueueLength":"0","WaitDisplay":"0","ProcessTime":"0"},{"key":"Counter 12","QueueLength":"0","WaitDisplay":"0","ProcessTime":"92"}],"QueueLength":0,"WaitDisplay":0,"ProcessTime":92}},"T1CI_34-86":{"MH":{"drilldown":[{"key":"Counter 68","QueueLength":"26","WaitDisplay":"780","ProcessTime":"0"}],"QueueLength":26,"WaitDisplay":780,"ProcessTime":0},"SQ":{"drilldown":[{"key":"Counter 79","QueueLength":"38","WaitDisplay":"480","ProcessTime":"0"},{"key":"Counter 80","QueueLength":"38","WaitDisplay":"480","ProcessTime":"0"},{"key":"Counter 81","QueueLength":"38","WaitDisplay":"480","ProcessTime":"55"},{"key":"Counter 82","QueueLength":"38","WaitDisplay":"480","ProcessTime":"53"},{"key":"Counter 83","QueueLength":"38","WaitDisplay":"480","ProcessTime":"0"},{"key":"Counter 84","QueueLength":"38","WaitDisplay":"480","ProcessTime":"0"},{"key":"Counter 85","QueueLength":"38","WaitDisplay":"480","ProcessTime":"0"},{"key":"Counter 86","QueueLength":"38","WaitDisplay":"480","ProcessTime":"0"}],"QueueLength":38,"WaitDisplay":480,"ProcessTime":55},"UK":{"drilldown":[{"key":"Counter 45","QueueLength":"0","WaitDisplay":"60","ProcessTime":"0"},{"key":"Counter 46","QueueLength":"0","WaitDisplay":"60","ProcessTime":"30"},{"key":"Counter 47","QueueLength":"0","WaitDisplay":"60","ProcessTime":"0"},{"key":"Counter 48","QueueLength":"0","WaitDisplay":"60","ProcessTime":"0"},{"key":"Counter 49","QueueLength":"0","WaitDisplay":"60","ProcessTime":"0"},{"key":"Counter 50","QueueLength":"0","WaitDisplay":"60","ProcessTime":"0"}],"QueueLength":0,"WaitDisplay":60,"ProcessTime":30},"FD":{"drilldown":[{"key":"Counter 74","QueueLength":"4","WaitDisplay":"60","ProcessTime":"0"},{"key":"Counter 75","QueueLength":"4","WaitDisplay":"60","ProcessTime":"0"},{"key":"Counter 76","QueueLength":"4","WaitDisplay":"60","ProcessTime":"0"},{"key":"Counter 77","QueueLength":"4","WaitDisplay":"60","ProcessTime":"0"}],"QueueLength":4,"WaitDisplay":60,"ProcessTime":0}}},"metadata":{"units":{"QueueLength":"#","WaitDisplay":"seconds","ProcessTime":"seconds"}},"status":200,"type":"success","message":"Data Fetched Successfully"}