{"data":{"T1IM":{"Queue":{"QueueLength":0,"WaitDisplay":120},"Desk":{"ProcessTime":0,"QueueLength":0},"Error":{}},"T1DE_5a-9":{"Queue":{"QueueLength":31,"WaitDisplay":120},"Desk":{"ProcessTime":41},"Error":{}},"T1VI":{"Queue":{"QueueLength":0,"WaitDisplay":0},"Desk":{"ProcessTime":0},"Error":{}},"T1DE_1-4":{"Queue":{"QueueLength":10,"WaitDisplay":0},"Desk":{"ProcessTime":64},"Error":{}},"T1DE_5":{"Queue":{"QueueLength":2,"WaitDisplay":0},"Desk":{"ProcessTime":21},"Error":{}},"T1EM":{"Queue":{"QueueLength":0,"WaitDisplay":0},"Desk":{"ProcessTime":57},"Error":{}},"T1BD":{"Queue":{"QueueLength":1,"WaitDisplay":120},"Desk":{"ProcessTime":0},"Error":{}},"T1DS_Right":{"Queue":{"QueueLength":27,"WaitDisplay":1440,"recommendation":{"bucket":"8","reference":"Lane 12+13","data":{"QueueId":"1024","QueueLength":"1","WaitB":"177","WaitF":"69","WaitDisplay":120,"Throughput":"99","ForwExits":"229790"},"code":"12+13"}},"Desk":{},"Error":{}},"T1IS":{"Queue":{"QueueLength":16,"WaitDisplay":360,"recommendation":{"data":{"WaitDisplay":999999}}},"Desk":{},"Error":{}},"T1DS_Left":{"Queue":{"QueueLength":21,"WaitDisplay":480,"recommendation":{"bucket":"6","reference":"Lane 8+9","data":{"QueueId":"1020","QueueLength":"12","WaitB":"102","WaitF":"252","WaitDisplay":240,"Throughput":"86","ForwExits":"50247"},"code":"8+9"}},"Desk":{"QueueLength":19,"ProcessTime":15},"Error":{}},"T1CI_01-33":{"6E":{"drilldown":[{"key":"Counter 13","QueueLength":"3","WaitDisplay":"0","ProcessTime":"0"},{"key":"Counter 14","QueueLength":"3","WaitDisplay":"0","ProcessTime":"0"},{"key":"Counter 15","QueueLength":"3","WaitDisplay":"0","ProcessTime":"50"},{"key":"Counter 16","QueueLength":"3","WaitDisplay":"0","ProcessTime":"52"},{"key":"Counter 17","QueueLength":"3","WaitDisplay":"0","ProcessTime":"84"},{"key":"Counter 18","QueueLength":"3","WaitDisplay":"0","ProcessTime":"75"},{"key":"Counter 19","QueueLength":"3","WaitDisplay":"0","ProcessTime":"0"},{"key":"Counter 20","QueueLength":"3","WaitDisplay":"0","ProcessTime":"0"},{"key":"Counter 21","QueueLength":"3","WaitDisplay":"0","ProcessTime":"0"},{"key":"Counter 22","QueueLength":"3","WaitDisplay":"0","ProcessTime":"0"},{"key":"Counter 23","QueueLength":"3","WaitDisplay":"0","ProcessTime":"68"},{"key":"Counter 24","QueueLength":"3","WaitDisplay":"0","ProcessTime":"0"},{"key":"Counter 25","QueueLength":"3","WaitDisplay":"0","ProcessTime":"0"},{"key":"Counter 26","QueueLength":"3","WaitDisplay":"0","ProcessTime":"0"},{"key":"Counter 27","QueueLength":"3","WaitDisplay":"0","ProcessTime":"61"},{"key":"Counter 28","QueueLength":"3","WaitDisplay":"0","ProcessTime":"141"},{"key":"Counter 29","QueueLength":"3","WaitDisplay":"0","ProcessTime":"51"},{"key":"Counter 30","QueueLength":"3","WaitDisplay":"0","ProcessTime":"71"},{"key":"Counter 31","QueueLength":"3","WaitDisplay":"0","ProcessTime":"84"},{"key":"Counter 32","QueueLength":"3","WaitDisplay":"0","ProcessTime":"90"},{"key":"Counter 33","QueueLength":"3","WaitDisplay":"0","ProcessTime":"0"}],"QueueLength":3,"WaitDisplay":0,"ProcessTime":141},"AI":{"drilldown":[{"key":"Counter 04","QueueLength":"7","WaitDisplay":"60","ProcessTime":"105"},{"key":"Counter 05","QueueLength":"7","WaitDisplay":"60","ProcessTime":"0"},{"key":"Counter 06","QueueLength":"7","WaitDisplay":"60","ProcessTime":"0"}],"QueueLength":7,"WaitDisplay":60,"ProcessTime":105}},"T1CI_34-86":{"AI":{"drilldown":[{"key":"Counter 79","QueueLength":"10","WaitDisplay":"120","ProcessTime":"0"},{"key":"Counter 80","QueueLength":"10","WaitDisplay":"120","ProcessTime":"70"},{"key":"Counter 81","QueueLength":"10","WaitDisplay":"120","ProcessTime":"35"},{"key":"Counter 82","QueueLength":"10","WaitDisplay":"120","ProcessTime":"45"},{"key":"Counter 83","QueueLength":"10","WaitDisplay":"120","ProcessTime":"0"},{"key":"Counter 84","QueueLength":"10","WaitDisplay":"120","ProcessTime":"25"},{"key":"Counter 86","QueueLength":"10","WaitDisplay":"120","ProcessTime":"103"}],"QueueLength":10,"WaitDisplay":120,"ProcessTime":103},"G8":{"drilldown":[{"key":"Counter 57","QueueLength":"0","WaitDisplay":"0","ProcessTime":"37"},{"key":"Counter 58","QueueLength":"0","WaitDisplay":"0","ProcessTime":"0"},{"key":"Counter 59","QueueLength":"0","WaitDisplay":"0","ProcessTime":"0"}],"QueueLength":0,"WaitDisplay":0,"ProcessTime":37},"SQ":{"drilldown":[{"key":"Counter 74","QueueLength":"0","WaitDisplay":"0","ProcessTime":"47"},{"key":"Counter 75","QueueLength":"0","WaitDisplay":"0","ProcessTime":"0"},{"key":"Counter 76","QueueLength":"0","WaitDisplay":"0","ProcessTime":"0"},{"key":"Counter 77","QueueLength":"0","WaitDisplay":"0","ProcessTime":"0"}],"QueueLength":0,"WaitDisplay":0,"ProcessTime":47},"UK":{"drilldown":[{"key":"Counter 44","QueueLength":"0","WaitDisplay":"0","ProcessTime":"0"},{"key":"Counter 45","QueueLength":"0","WaitDisplay":"0","ProcessTime":"0"},{"key":"Counter 46","QueueLength":"0","WaitDisplay":"0","ProcessTime":"75"},{"key":"Counter 47","QueueLength":"0","WaitDisplay":"0","ProcessTime":"192"},{"key":"Counter 48","QueueLength":"0","WaitDisplay":"0","ProcessTime":"55"},{"key":"Counter 49","QueueLength":"0","WaitDisplay":"0","ProcessTime":"0"},{"key":"Counter 50","QueueLength":"0","WaitDisplay":"0","ProcessTime":"0"}],"QueueLength":0,"WaitDisplay":0,"ProcessTime":192},"QP":{"drilldown":[{"key":"Counter 63","QueueLength":"0","WaitDisplay":"0","ProcessTime":"0"},{"key":"Counter 64","QueueLength":"0","WaitDisplay":"0","ProcessTime":"0"},{"key":"Counter 65","QueueLength":"0","WaitDisplay":"0","ProcessTime":"43"},{"key":"Counter 66","QueueLength":"0","WaitDisplay":"0","ProcessTime":"0"},{"key":"Counter 67","QueueLength":"0","WaitDisplay":"0","ProcessTime":"0"},{"key":"Counter 68","QueueLength":"0","WaitDisplay":"0","ProcessTime":"0"},{"key":"Counter 69","QueueLength":"0","WaitDisplay":"0","ProcessTime":"0"},{"key":"Counter 70","QueueLength":"0","WaitDisplay":"0","ProcessTime":"0"}],"QueueLength":0,"WaitDisplay":0,"ProcessTime":43}}},"metadata":{"units":{"QueueLength":"#","WaitDisplay":"seconds","ProcessTime":"seconds"}},"status":200,"type":"success","message":"Data Fetched Successfully"}