{"data":{"T1CI_01-33":{},"T1IM":{},"T1BD":{},"T1VI":{},"T1DE_5a-9":{},"T1EM":{},"T1DE_1-4":{},"T1DE_5":{"Queue":{"QueueLength":0,"WaitDisplay":0},"Desk":{"ProcessTime":0},"Error":{}},"T1CI_34-86":{"6E":{"QueueLength":-1,"WaitDisplay":-1,"ProcessTime":-1}},"T1IS":{"Queue":{"QueueLength":2,"WaitDisplay":120,"recommendation":{"data":{"WaitDisplay":999999}}},"Desk":{},"Error":{}},"T1DS_Left":{"Queue":{"QueueLength":1,"WaitDisplay":120,"recommendation":{"data":{"WaitDisplay":999999}}},"Desk":{"QueueLength":1,"ProcessTime":16},"Error":{}}},"metadata":{"units":{"QueueLength":"#","WaitDisplay":"seconds","ProcessTime":"seconds"}},"status":200,"type":"success","message":"Data Fetched Successfully"}