{"data":{"T1IM":{"Queue":{"QueueLength":185,"WaitDisplay":1800},"Desk":{"ProcessTime":298,"QueueLength":49},"Error":{}},"T1DE_5":{"Queue":{"QueueLength":1,"WaitDisplay":60},"Desk":{"ProcessTime":0},"Error":{}},"T1VI":{"Queue":{"QueueLength":11,"WaitDisplay":180},"Desk":{"ProcessTime":155},"Error":{}},"T1DE_1-4":{"Queue":{"QueueLength":20,"WaitDisplay":60},"Desk":{"ProcessTime":25},"Error":{}},"T1DE_5a-9":{"Queue":{"QueueLength":60,"WaitDisplay":240},"Desk":{"ProcessTime":51},"Error":{}},"T1EM":{"Queue":{"QueueLength":87,"WaitDisplay":540},"Desk":{"ProcessTime":207},"Error":{}},"T1BD":{"Queue":{"QueueLength":2,"WaitDisplay":180},"Desk":{"ProcessTime":0},"Error":{}},"T1DS_Right":{"Queue":{"QueueLength":26,"WaitDisplay":2220,"recommendation":{"bucket":"7","reference":"Lane 10+11","data":{"QueueId":"1022","QueueLength":"26","WaitB":"947","WaitF":"2196","WaitDisplay":2220,"Throughput":"49","ForwExits":"345212"},"code":"10+11"}},"Desk":{},"Error":{}},"T1IS":{"Queue":{"QueueLength":15,"WaitDisplay":600,"recommendation":{"data":{"WaitDisplay":999999}}},"Desk":{},"Error":{}},"T1DS_Left":{"Queue":{"QueueLength":25,"WaitDisplay":360,"recommendation":{"bucket":"1","reference":"Lane 1","data":{"QueueId":"1012","QueueLength":"10","WaitB":"126","WaitF":"155","WaitDisplay":120,"Throughput":"210","ForwExits":"51405"},"code":"1"}},"Desk":{"QueueLength":10,"ProcessTime":19},"Error":{}},"T1CI_34-86":{"EK":{"drilldown":[{"key":"Counter 75","QueueLength":"10","WaitDisplay":"60","ProcessTime":"0"},{"key":"Counter 76","QueueLength":"10","WaitDisplay":"60","ProcessTime":"0"},{"key":"Counter 77","QueueLength":"10","WaitDisplay":"60","ProcessTime":"0"},{"key":"Counter 78","QueueLength":"10","WaitDisplay":"60","ProcessTime":"95"},{"key":"Counter 79","QueueLength":"10","WaitDisplay":"60","ProcessTime":"0"},{"key":"Counter 80","QueueLength":"10","WaitDisplay":"60","ProcessTime":"0"},{"key":"Counter 81","QueueLength":"10","WaitDisplay":"60","ProcessTime":"0"},{"key":"Counter 82","QueueLength":"10","WaitDisplay":"60","ProcessTime":"0"},{"key":"Counter 83","QueueLength":"10","WaitDisplay":"60","ProcessTime":"0"},{"key":"Counter 84","QueueLength":"10","WaitDisplay":"60","ProcessTime":"0"},{"key":"Counter 85","QueueLength":"10","WaitDisplay":"60","ProcessTime":"0"},{"key":"Counter 86","QueueLength":"10","WaitDisplay":"60","ProcessTime":"0"}],"QueueLength":10,"WaitDisplay":60,"ProcessTime":95},"G8":{"drilldown":[{"key":"Counter 57","QueueLength":"9","WaitDisplay":"180","ProcessTime":"89"},{"key":"Counter 58","QueueLength":"9","WaitDisplay":"180","ProcessTime":"46"},{"key":"Counter 59","QueueLength":"9","WaitDisplay":"180","ProcessTime":"0"}],"QueueLength":9,"WaitDisplay":180,"ProcessTime":89},"I5":{"drilldown":[{"key":"Counter 34","QueueLength":"51","WaitDisplay":"660","ProcessTime":"0"},{"key":"Counter 35","QueueLength":"51","WaitDisplay":"660","ProcessTime":"0"},{"key":"Counter 36","QueueLength":"51","WaitDisplay":"660","ProcessTime":"0"},{"key":"Counter 37","QueueLength":"51","WaitDisplay":"660","ProcessTime":"86"},{"key":"Counter 38","QueueLength":"51","WaitDisplay":"660","ProcessTime":"49"},{"key":"Counter 39","QueueLength":"51","WaitDisplay":"660","ProcessTime":"45"},{"key":"Counter 40","QueueLength":"51","WaitDisplay":"660","ProcessTime":"44"}],"QueueLength":51,"WaitDisplay":660,"ProcessTime":86}},"T1CI_01-33":{"6E":{"drilldown":[{"key":"Counter 21","QueueLength":"87","WaitDisplay":"360","ProcessTime":"35"},{"key":"Counter 22","QueueLength":"87","WaitDisplay":"360","ProcessTime":"52"},{"key":"Counter 23","QueueLength":"87","WaitDisplay":"360","ProcessTime":"0"},{"key":"Counter 24","QueueLength":"87","WaitDisplay":"360","ProcessTime":"0"},{"key":"Counter 25","QueueLength":"87","WaitDisplay":"360","ProcessTime":"0"},{"key":"Counter 26","QueueLength":"87","WaitDisplay":"360","ProcessTime":"93"},{"key":"Counter 27","QueueLength":"87","WaitDisplay":"360","ProcessTime":"0"},{"key":"Counter 28","QueueLength":"87","WaitDisplay":"360","ProcessTime":"0"},{"key":"Counter 29","QueueLength":"87","WaitDisplay":"360","ProcessTime":"107"},{"key":"Counter 30","QueueLength":"87","WaitDisplay":"360","ProcessTime":"65"},{"key":"Counter 31","QueueLength":"87","WaitDisplay":"360","ProcessTime":"85"},{"key":"Counter 32","QueueLength":"87","WaitDisplay":"360","ProcessTime":"0"},{"key":"Counter 33","QueueLength":"87","WaitDisplay":"360","ProcessTime":"46"}],"QueueLength":87,"WaitDisplay":360,"ProcessTime":107},"EY":{"drilldown":[{"key":"Counter 13","QueueLength":"0","WaitDisplay":"0","ProcessTime":"0"},{"key":"Counter 14","QueueLength":"0","WaitDisplay":"0","ProcessTime":"0"},{"key":"Counter 15","QueueLength":"0","WaitDisplay":"0","ProcessTime":"0"},{"key":"Counter 16","QueueLength":"0","WaitDisplay":"0","ProcessTime":"0"},{"key":"Counter 17","QueueLength":"0","WaitDisplay":"0","ProcessTime":"0"},{"key":"Counter 18","QueueLength":"0","WaitDisplay":"0","ProcessTime":"0"},{"key":"Counter 19","QueueLength":"0","WaitDisplay":"0","ProcessTime":"0"},{"key":"Counter 20","QueueLength":"0","WaitDisplay":"0","ProcessTime":"0"}],"QueueLength":0,"WaitDisplay":0,"ProcessTime":0},"GF":{"drilldown":[{"key":"Counter 04","QueueLength":"12","WaitDisplay":"120","ProcessTime":"40"},{"key":"Counter 05","QueueLength":"12","WaitDisplay":"120","ProcessTime":"0"},{"key":"Counter 06","QueueLength":"12","WaitDisplay":"120","ProcessTime":"45"},{"key":"Counter 07","QueueLength":"12","WaitDisplay":"120","ProcessTime":"0"}],"QueueLength":12,"WaitDisplay":120,"ProcessTime":45}}},"metadata":{"units":{"QueueLength":"#","WaitDisplay":"seconds","ProcessTime":"seconds"}},"status":200,"type":"success","message":"Data Fetched Successfully"}