{"data":{"T1IM":{"Queue":{"QueueLength":0,"WaitDisplay":120},"Desk":{"ProcessTime":0,"QueueLength":0},"Error":{}},"T1DE_5":{"Queue":{"QueueLength":0,"WaitDisplay":0},"Desk":{"ProcessTime":0},"Error":{}},"T1DE_5a-9":{"Queue":{"QueueLength":28,"WaitDisplay":120},"Desk":{"ProcessTime":25},"Error":{}},"T1DE_1-4":{"Queue":{"QueueLength":28,"WaitDisplay":60},"Desk":{"ProcessTime":73},"Error":{}},"T1VI":{"Queue":{"QueueLength":0,"WaitDisplay":0},"Desk":{"ProcessTime":0},"Error":{}},"T1BD":{"Queue":{"QueueLength":1,"WaitDisplay":60},"Desk":{"ProcessTime":32},"Error":{}},"T1EM":{"Queue":{"QueueLength":0,"WaitDisplay":0},"Desk":{"ProcessTime":120},"Error":{}},"T1DS_Right":{"Queue":{"QueueLength":5,"WaitDisplay":120,"recommendation":{"bucket":"7","reference":"Lane 10+11","data":{"QueueId":"1022","QueueLength":"0","WaitB":"1","WaitF":"29","WaitDisplay":120,"Throughput":"61","ForwExits":"333695"},"code":"10+11"}},"Desk":{},"Error":{}},"T1IS":{"Queue":{"QueueLength":15,"WaitDisplay":300,"recommendation":{"data":{"WaitDisplay":999999}}},"Desk":{},"Error":{}},"T1DS_Left":{"Queue":{"QueueLength":11,"WaitDisplay":180,"recommendation":{"bucket":"2","reference":"Lane 2+3","data":{"QueueId":"1014","QueueLength":"2","WaitB":"40","WaitF":"70","WaitDisplay":60,"Throughput":"74","ForwExits":"33181"},"code":"2+3"}},"Desk":{"QueueLength":5,"ProcessTime":16},"Error":{}},"T1CI_01-33":{"AI":{"drilldown":[{"key":"Counter 04","QueueLength":"11","WaitDisplay":"240","ProcessTime":"0"},{"key":"Counter 05","QueueLength":"11","WaitDisplay":"240","ProcessTime":"0"},{"key":"Counter 06","QueueLength":"11","WaitDisplay":"240","ProcessTime":"153"}],"QueueLength":11,"WaitDisplay":240,"ProcessTime":153}},"T1CI_34-86":{"6E":{"drilldown":[{"key":"Counter 41","QueueLength":"17","WaitDisplay":"480","ProcessTime":"0"},{"key":"Counter 42","QueueLength":"17","WaitDisplay":"480","ProcessTime":"0"},{"key":"Counter 43","QueueLength":"17","WaitDisplay":"480","ProcessTime":"0"}],"QueueLength":17,"WaitDisplay":480,"ProcessTime":0},"SQ":{"drilldown":[{"key":"Counter 75","QueueLength":"1","WaitDisplay":"0","ProcessTime":"0"},{"key":"Counter 76","QueueLength":"1","WaitDisplay":"0","ProcessTime":"0"},{"key":"Counter 77","QueueLength":"1","WaitDisplay":"0","ProcessTime":"0"},{"key":"Counter 78","QueueLength":"1","WaitDisplay":"0","ProcessTime":"0"}],"QueueLength":1,"WaitDisplay":0,"ProcessTime":0}}},"metadata":{"units":{"QueueLength":"#","WaitDisplay":"seconds","ProcessTime":"seconds"}},"status":200,"type":"success","message":"Data Fetched Successfully"}