{"data":{"T1CI_01-33":{},"T1IM":{"Queue":{"QueueLength":0,"WaitDisplay":120},"Desk":{"ProcessTime":0,"QueueLength":0},"Error":{}},"T1VI":{"Queue":{"QueueLength":0,"WaitDisplay":60},"Desk":{"ProcessTime":0},"Error":{}},"T1DE_1-4":{"Queue":{"QueueLength":3,"WaitDisplay":60},"Desk":{"ProcessTime":18},"Error":{}},"T1DE_5":{"Queue":{"QueueLength":0,"WaitDisplay":0},"Desk":{"ProcessTime":0},"Error":{}},"T1DE_5a-9":{"Queue":{"QueueLength":16,"WaitDisplay":120},"Desk":{"ProcessTime":96},"Error":{}},"T1BD":{"Queue":{"QueueLength":0,"WaitDisplay":60},"Desk":{"ProcessTime":0},"Error":{}},"T1EM":{"Queue":{"QueueLength":0,"WaitDisplay":0},"Desk":{"ProcessTime":0},"Error":{}},"T1DS_Right":{"Queue":{"QueueLength":4,"WaitDisplay":120,"recommendation":{"bucket":"7","reference":"Lane 10+11","data":{"QueueId":"1022","QueueLength":"4","WaitB":"10","WaitF":"149","WaitDisplay":120,"Throughput":"61","ForwExits":"331231"},"code":"10+11"}},"Desk":{},"Error":{}},"T1DS_Left":{"Queue":{"QueueLength":5,"WaitDisplay":240,"recommendation":{"bucket":"3","reference":"Lane 4+5","data":{"QueueId":"1016","QueueLength":"0","WaitB":"0","WaitF":"30","WaitDisplay":120,"Throughput":"24","ForwExits":"50813"},"code":"4+5"}},"Desk":{"QueueLength":2,"ProcessTime":15},"Error":{}},"T1IS":{"Queue":{"QueueLength":2,"WaitDisplay":120,"recommendation":{"data":{"WaitDisplay":999999}}},"Desk":{},"Error":{}},"T1CI_34-86":{"I5":{"drilldown":[{"key":"Counter 81","QueueLength":"0","WaitDisplay":"0","ProcessTime":"0"},{"key":"Counter 82","QueueLength":"0","WaitDisplay":"0","ProcessTime":"0"},{"key":"Counter 83","QueueLength":"0","WaitDisplay":"0","ProcessTime":"0"},{"key":"Counter 84","QueueLength":"0","WaitDisplay":"0","ProcessTime":"0"},{"key":"Counter 85","QueueLength":"0","WaitDisplay":"0","ProcessTime":"0"},{"key":"Counter 86","QueueLength":"0","WaitDisplay":"0","ProcessTime":"0"}],"QueueLength":0,"WaitDisplay":0,"ProcessTime":0}}},"metadata":{"units":{"QueueLength":"#","WaitDisplay":"seconds","ProcessTime":"seconds"}},"status":200,"type":"success","message":"Data Fetched Successfully"}