{"data":{"T1IM":{"Queue":{"QueueLength":25,"WaitDisplay":180},"Desk":{"ProcessTime":148,"QueueLength":11},"Error":{}},"T1DE_5":{"Queue":{"QueueLength":2,"WaitDisplay":60},"Desk":{"ProcessTime":15},"Error":{}},"T1DE_1-4":{"Queue":{"QueueLength":61,"WaitDisplay":120},"Desk":{"ProcessTime":40},"Error":{}},"T1VI":{"Queue":{"QueueLength":4,"WaitDisplay":240},"Desk":{"ProcessTime":0},"Error":{}},"T1DE_5a-9":{"Queue":{"QueueLength":77,"WaitDisplay":300},"Desk":{"ProcessTime":39},"Error":{}},"T1EM":{"Queue":{"QueueLength":0,"WaitDisplay":0},"Desk":{"ProcessTime":42},"Error":{}},"T1BD":{"Queue":{"QueueLength":0,"WaitDisplay":60},"Desk":{"ProcessTime":0},"Error":{}},"T1DS_Right":{"Queue":{"QueueLength":12,"WaitDisplay":300,"recommendation":{"bucket":"7","reference":"Lane 10+11","data":{"QueueId":"1022","QueueLength":"8","WaitB":"410","WaitF":"190","WaitDisplay":180,"Throughput":"185","ForwExits":"292681"},"code":"10+11"}},"Desk":{},"Error":{}},"T1IS":{"Queue":{"QueueLength":6,"WaitDisplay":180,"recommendation":{"data":{"WaitDisplay":999999}}},"Desk":{},"Error":{}},"T1DS_Left":{"Queue":{"QueueLength":20,"WaitDisplay":780,"recommendation":{"bucket":"2","reference":"Lane 2+3","data":{"QueueId":"1014","QueueLength":"12","WaitB":"230","WaitF":"243","WaitDisplay":180,"Throughput":"123","ForwExits":"10245"},"code":"2+3"}},"Desk":{"QueueLength":17,"ProcessTime":22},"Error":{}},"T1CI_01-33":{"6E":{"drilldown":[{"key":"Counter 13","QueueLength":"7","WaitDisplay":"0","ProcessTime":"0"},{"key":"Counter 14","QueueLength":"7","WaitDisplay":"0","ProcessTime":"0"},{"key":"Counter 15","QueueLength":"7","WaitDisplay":"0","ProcessTime":"0"},{"key":"Counter 16","QueueLength":"7","WaitDisplay":"0","ProcessTime":"0"},{"key":"Counter 17","QueueLength":"7","WaitDisplay":"0","ProcessTime":"0"},{"key":"Counter 18","QueueLength":"7","WaitDisplay":"0","ProcessTime":"65"},{"key":"Counter 19","QueueLength":"7","WaitDisplay":"0","ProcessTime":"59"},{"key":"Counter 20","QueueLength":"7","WaitDisplay":"0","ProcessTime":"0"},{"key":"Counter 21","QueueLength":"7","WaitDisplay":"0","ProcessTime":"64"},{"key":"Counter 22","QueueLength":"7","WaitDisplay":"0","ProcessTime":"0"},{"key":"Counter 23","QueueLength":"7","WaitDisplay":"0","ProcessTime":"110"},{"key":"Counter 24","QueueLength":"7","WaitDisplay":"0","ProcessTime":"0"},{"key":"Counter 25","QueueLength":"7","WaitDisplay":"0","ProcessTime":"0"},{"key":"Counter 26","QueueLength":"7","WaitDisplay":"0","ProcessTime":"52"},{"key":"Counter 27","QueueLength":"7","WaitDisplay":"0","ProcessTime":"75"},{"key":"Counter 28","QueueLength":"7","WaitDisplay":"0","ProcessTime":"64"},{"key":"Counter 29","QueueLength":"7","WaitDisplay":"0","ProcessTime":"0"},{"key":"Counter 30","QueueLength":"7","WaitDisplay":"0","ProcessTime":"0"},{"key":"Counter 31","QueueLength":"7","WaitDisplay":"0","ProcessTime":"98"},{"key":"Counter 32","QueueLength":"7","WaitDisplay":"0","ProcessTime":"0"},{"key":"Counter 33","QueueLength":"7","WaitDisplay":"0","ProcessTime":"0"}],"QueueLength":7,"WaitDisplay":0,"ProcessTime":110},"AI":{"drilldown":[{"key":"Counter 06","QueueLength":"0","WaitDisplay":"0","ProcessTime":"0"},{"key":"Counter 07","QueueLength":"0","WaitDisplay":"0","ProcessTime":"28"},{"key":"Counter 08","QueueLength":"0","WaitDisplay":"0","ProcessTime":"0"},{"key":"Counter 09","QueueLength":"0","WaitDisplay":"0","ProcessTime":"0"},{"key":"Counter 10","QueueLength":"0","WaitDisplay":"0","ProcessTime":"0"}],"QueueLength":0,"WaitDisplay":0,"ProcessTime":28},"SG":{"drilldown":[{"key":"Counter 01","QueueLength":"10","WaitDisplay":"180","ProcessTime":"0"},{"key":"Counter 02","QueueLength":"10","WaitDisplay":"180","ProcessTime":"0"},{"key":"Counter 03","QueueLength":"10","WaitDisplay":"180","ProcessTime":"79"},{"key":"Counter 04","QueueLength":"10","WaitDisplay":"180","ProcessTime":"27"}],"QueueLength":10,"WaitDisplay":180,"ProcessTime":79},"9I":{"drilldown":[{"key":"Counter 11","QueueLength":"0","WaitDisplay":"0","ProcessTime":"57"},{"key":"Counter 12","QueueLength":"0","WaitDisplay":"0","ProcessTime":"81"}],"QueueLength":0,"WaitDisplay":0,"ProcessTime":81}},"T1CI_34-86":{"BA":{"drilldown":[{"key":"Counter 71","QueueLength":"0","WaitDisplay":"0","ProcessTime":"0"},{"key":"Counter 72","QueueLength":"0","WaitDisplay":"0","ProcessTime":"0"},{"key":"Counter 73","QueueLength":"0","WaitDisplay":"0","ProcessTime":"0"},{"key":"Counter 74","QueueLength":"0","WaitDisplay":"0","ProcessTime":"0"},{"key":"Counter 75","QueueLength":"0","WaitDisplay":"0","ProcessTime":"0"},{"key":"Counter 76","QueueLength":"0","WaitDisplay":"0","ProcessTime":"0"},{"key":"Counter 77","QueueLength":"0","WaitDisplay":"0","ProcessTime":"0"},{"key":"Counter 78","QueueLength":"0","WaitDisplay":"0","ProcessTime":"0"}],"QueueLength":0,"WaitDisplay":0,"ProcessTime":0},"G8":{"drilldown":[{"key":"Counter 34","QueueLength":"45","WaitDisplay":"600","ProcessTime":"0"},{"key":"Counter 35","QueueLength":"45","WaitDisplay":"600","ProcessTime":"0"},{"key":"Counter 36","QueueLength":"45","WaitDisplay":"600","ProcessTime":"32"},{"key":"Counter 37","QueueLength":"45","WaitDisplay":"600","ProcessTime":"0"},{"key":"Counter 38","QueueLength":"45","WaitDisplay":"600","ProcessTime":"82"},{"key":"Counter 39","QueueLength":"45","WaitDisplay":"600","ProcessTime":"72"},{"key":"Counter 40","QueueLength":"45","WaitDisplay":"600","ProcessTime":"0"}],"QueueLength":45,"WaitDisplay":600,"ProcessTime":82},"I5":{"drilldown":[{"key":"Counter 53","QueueLength":"2","WaitDisplay":"60","ProcessTime":"0"},{"key":"Counter 54","QueueLength":"2","WaitDisplay":"60","ProcessTime":"0"},{"key":"Counter 55","QueueLength":"2","WaitDisplay":"60","ProcessTime":"0"},{"key":"Counter 56","QueueLength":"2","WaitDisplay":"60","ProcessTime":"40"},{"key":"Counter 57","QueueLength":"2","WaitDisplay":"60","ProcessTime":"48"},{"key":"Counter 58","QueueLength":"2","WaitDisplay":"60","ProcessTime":"0"},{"key":"Counter 59","QueueLength":"2","WaitDisplay":"60","ProcessTime":"0"},{"key":"Counter 60","QueueLength":"2","WaitDisplay":"60","ProcessTime":"0"}],"QueueLength":2,"WaitDisplay":60,"ProcessTime":48},"UK":{"drilldown":[{"key":"Counter 44","QueueLength":"30","WaitDisplay":"300","ProcessTime":"52"},{"key":"Counter 45","QueueLength":"30","WaitDisplay":"300","ProcessTime":"0"},{"key":"Counter 46","QueueLength":"30","WaitDisplay":"300","ProcessTime":"43"},{"key":"Counter 47","QueueLength":"30","WaitDisplay":"300","ProcessTime":"0"},{"key":"Counter 48","QueueLength":"30","WaitDisplay":"300","ProcessTime":"0"},{"key":"Counter 49","QueueLength":"30","WaitDisplay":"300","ProcessTime":"42"},{"key":"Counter 50","QueueLength":"30","WaitDisplay":"300","ProcessTime":"0"}],"QueueLength":30,"WaitDisplay":300,"ProcessTime":52},"QP":{"drilldown":[{"key":"Counter 63","QueueLength":"0","WaitDisplay":"0","ProcessTime":"0"},{"key":"Counter 64","QueueLength":"0","WaitDisplay":"0","ProcessTime":"0"},{"key":"Counter 65","QueueLength":"0","WaitDisplay":"0","ProcessTime":"0"},{"key":"Counter 66","QueueLength":"0","WaitDisplay":"0","ProcessTime":"55"},{"key":"Counter 67","QueueLength":"0","WaitDisplay":"0","ProcessTime":"55"},{"key":"Counter 68","QueueLength":"0","WaitDisplay":"0","ProcessTime":"32"},{"key":"Counter 69","QueueLength":"0","WaitDisplay":"0","ProcessTime":"0"},{"key":"Counter 70","QueueLength":"0","WaitDisplay":"0","ProcessTime":"0"}],"QueueLength":0,"WaitDisplay":0,"ProcessTime":55}}},"metadata":{"units":{"QueueLength":"#","WaitDisplay":"seconds","ProcessTime":"seconds"}},"status":200,"type":"success","message":"Data Fetched Successfully"}