{"data":{"T1IM":{"Queue":{"QueueLength":6,"WaitDisplay":120},"Desk":{"ProcessTime":114,"QueueLength":0},"Error":{}},"T1EM":{"Queue":{"QueueLength":39,"WaitDisplay":480},"Desk":{"ProcessTime":92},"Error":{}},"T1BD":{"Queue":{"QueueLength":1,"WaitDisplay":60},"Desk":{"ProcessTime":0},"Error":{}},"T1VI":{"Queue":{"QueueLength":2,"WaitDisplay":180},"Desk":{"ProcessTime":0},"Error":{}},"T1DE_1-4":{"Queue":{"QueueLength":5,"WaitDisplay":60},"Desk":{"ProcessTime":0},"Error":{}},"T1DE_5a-9":{"Queue":{"QueueLength":1,"WaitDisplay":0},"Desk":{"ProcessTime":29},"Error":{}},"T1DE_5":{"Queue":{"QueueLength":1,"WaitDisplay":60},"Desk":{"ProcessTime":0},"Error":{}},"T1DS_Right":{"Queue":{"QueueLength":2,"WaitDisplay":120,"recommendation":{"bucket":"7","reference":"Lane 10+11","data":{"QueueId":"1022","QueueLength":"1","WaitB":"38","WaitF":"90","WaitDisplay":120,"Throughput":"37","ForwExits":"470524"},"code":"10+11"}},"Desk":{},"Error":{}},"T1IS":{"Queue":{"QueueLength":15,"recommendation":{"data":{"WaitDisplay":999999}}},"Desk":{},"Error":{}},"T1DS_Left":{"Queue":{"QueueLength":4,"WaitDisplay":120,"recommendation":{"bucket":"2","reference":"Lane 2+3","data":{"QueueId":"1014","QueueLength":"1","WaitB":"0","WaitF":"68","WaitDisplay":0,"Throughput":"24","ForwExits":"125497"},"code":"2+3"}},"Desk":{"QueueLength":2,"ProcessTime":290},"Error":{}},"T1CI_01-33":{"6E":{"drilldown":[{"key":"Counter 25","QueueLength":"0","WaitDisplay":"0","ProcessTime":"0"},{"key":"Counter 26","QueueLength":"0","WaitDisplay":"0","ProcessTime":"106"},{"key":"Counter 27","QueueLength":"0","WaitDisplay":"0","ProcessTime":"0"},{"key":"Counter 28","QueueLength":"0","WaitDisplay":"0","ProcessTime":"31"},{"key":"Counter 29","QueueLength":"0","WaitDisplay":"0","ProcessTime":"100"},{"key":"Counter 30","QueueLength":"0","WaitDisplay":"0","ProcessTime":"0"},{"key":"Counter 31","QueueLength":"0","WaitDisplay":"0","ProcessTime":"0"},{"key":"Counter 32","QueueLength":"0","WaitDisplay":"0","ProcessTime":"0"},{"key":"Counter 33","QueueLength":"0","WaitDisplay":"0","ProcessTime":"0"}],"QueueLength":0,"WaitDisplay":0,"ProcessTime":106}},"T1CI_34-86":{"MH":{"drilldown":[{"key":"Counter 65","QueueLength":"0","WaitDisplay":"0","ProcessTime":"0"},{"key":"Counter 66","QueueLength":"0","WaitDisplay":"0","ProcessTime":"180"},{"key":"Counter 67","QueueLength":"0","WaitDisplay":"0","ProcessTime":"63"},{"key":"Counter 68","QueueLength":"0","WaitDisplay":"0","ProcessTime":"0"},{"key":"Counter 69","QueueLength":"0","WaitDisplay":"0","ProcessTime":"0"},{"key":"Counter 70","QueueLength":"0","WaitDisplay":"0","ProcessTime":"0"}],"QueueLength":0,"WaitDisplay":0,"ProcessTime":180},"FD":{"drilldown":[{"key":"Counter 39","QueueLength":"0","WaitDisplay":"0","ProcessTime":"0"},{"key":"Counter 40","QueueLength":"0","WaitDisplay":"0","ProcessTime":"0"},{"key":"Counter 41","QueueLength":"0","WaitDisplay":"0","ProcessTime":"0"},{"key":"Counter 42","QueueLength":"0","WaitDisplay":"0","ProcessTime":"0"}],"QueueLength":0,"WaitDisplay":0,"ProcessTime":0},"TG":{"drilldown":[{"key":"Counter 79","QueueLength":"26","WaitDisplay":"300","ProcessTime":"0"},{"key":"Counter 80","QueueLength":"26","WaitDisplay":"300","ProcessTime":"20"},{"key":"Counter 81","QueueLength":"26","WaitDisplay":"300","ProcessTime":"0"},{"key":"Counter 82","QueueLength":"26","WaitDisplay":"300","ProcessTime":"144"},{"key":"Counter 83","QueueLength":"26","WaitDisplay":"300","ProcessTime":"84"},{"key":"Counter 84","QueueLength":"26","WaitDisplay":"300","ProcessTime":"0"},{"key":"Counter 85","QueueLength":"26","WaitDisplay":"300","ProcessTime":"63"},{"key":"Counter 86","QueueLength":"26","WaitDisplay":"300","ProcessTime":"0"}],"QueueLength":26,"WaitDisplay":300,"ProcessTime":144},"CX":{"drilldown":[{"key":"Counter 53","QueueLength":"6","WaitDisplay":"60","ProcessTime":"0"},{"key":"Counter 54","QueueLength":"6","WaitDisplay":"60","ProcessTime":"0"},{"key":"Counter 55","QueueLength":"6","WaitDisplay":"60","ProcessTime":"0"},{"key":"Counter 56","QueueLength":"6","WaitDisplay":"60","ProcessTime":"0"},{"key":"Counter 57","QueueLength":"6","WaitDisplay":"60","ProcessTime":"89"},{"key":"Counter 58","QueueLength":"6","WaitDisplay":"60","ProcessTime":"0"},{"key":"Counter 59","QueueLength":"6","WaitDisplay":"60","ProcessTime":"0"},{"key":"Counter 60","QueueLength":"6","WaitDisplay":"60","ProcessTime":"67"}],"QueueLength":6,"WaitDisplay":60,"ProcessTime":89}}},"metadata":{"units":{"QueueLength":"#","WaitDisplay":"seconds","ProcessTime":"seconds"}},"status":200,"type":"success","message":"Data Fetched Successfully"}